AUTHORS
ChangeLog
LICENSE
MANIFEST.in
README.rst
requirements.txt
setup.cfg
setup.py
test-requirements.txt
tox.ini
bin/gerritexec
gerritexec/__init__.py
gerritexec/main.py
gerritexec.egg-info/PKG-INFO
gerritexec.egg-info/SOURCES.txt
gerritexec.egg-info/dependency_links.txt
gerritexec.egg-info/requires.txt
gerritexec.egg-info/top_level.txt
tests/test_gerritexec.py