Metadata-Version: 1.1
Name: gerritexec
Version: 1.0.0.a6.g53e06ae
Summary: Run a command when a gerrit patchset is created
Home-page: https://gitorious.org/gerritexec
Author: Loic Dachary
Author-email: loic@dachary.org
License: UNKNOWN
Platform: UNKNOWN
Classifier: Environment :: No Input/Output (Daemon)
Classifier: Intended Audience :: Information Technology
Classifier: Intended Audience :: System Administrators
Classifier: Operating System :: POSIX :: Linux
Classifier: License :: OSI Approved :: GNU Affero General Public License v3 or later (AGPLv3+)
Classifier: Programming Language :: Python
Classifier: Programming Language :: Python :: 2.7
Classifier: Topic :: Utilities
